[
  {
    "title": "Maurice Schirm - ReworkCM",
    "startTime": 1729987200,
    "startTimeReadable": "Sun, 27 Oct 2024 00:00:00 GMT",
    "duration": 251
  },
  {
    "title": "Scandinavian Star - Relic",
    "startTime": 1729987451,
    "startTimeReadable": "Sun, 27 Oct 2024 00:04:11 GMT",
    "duration": 104
  },
  {
    "title": "Emilia Haar - Yael",
    "startTime": 1729987555,
    "startTimeReadable": "Sun, 27 Oct 2024 00:05:55 GMT",
    "duration": 388
  },
  {
    "title": "Scandinavian Star - Alang",
    "startTime": 1729987943,
    "startTimeReadable": "Sun, 27 Oct 2024 00:12:23 GMT",
    "duration": 301
  },
  {
    "title": "Asan Tone - In Everyone Repeating",
    "startTime": 1729988244,
    "startTimeReadable": "Sun, 27 Oct 2024 00:17:24 GMT",
    "duration": 30
  },
  {
    "title": "Daisuke Tanabe - Hikemasen",
    "startTime": 1729988274,
    "startTimeReadable": "Sun, 27 Oct 2024 00:17:54 GMT",
    "duration": 407
  },
  {
    "title": "Medici Daughter - Snitch",
    "startTime": 1729988681,
    "startTimeReadable": "Sun, 27 Oct 2024 00:24:41 GMT",
    "duration": 118
  },
  {
    "title": "Asan Tone - Visit from Tokay",
    "startTime": 1729988799,
    "startTimeReadable": "Sun, 27 Oct 2024 00:26:39 GMT",
    "duration": 30
  },
  {
    "title": "Orchid - Retrieval",
    "startTime": 1729988829,
    "startTimeReadable": "Sun, 27 Oct 2024 00:27:09 GMT",
    "duration": 275
  },
  {
    "title": "Medici Daughter - Insolid",
    "startTime": 1729989104,
    "startTimeReadable": "Sun, 27 Oct 2024 00:31:44 GMT",
    "duration": 146
  },
  {
    "title": "Orchid - Heavenly Memory",
    "startTime": 1729989250,
    "startTimeReadable": "Sun, 27 Oct 2024 00:34:10 GMT",
    "duration": 202
  },
  {
    "title": "@-!3_&-7 9034-594 - Warter",
    "startTime": 1729989452,
    "startTimeReadable": "Sun, 27 Oct 2024 00:37:32 GMT",
    "duration": 276
  },
  {
    "title": "Cyber Sonic - Android Aura",
    "startTime": 1729989728,
    "startTimeReadable": "Sun, 27 Oct 2024 00:42:08 GMT",
    "duration": 79
  },
  {
    "title": "Huong Federkeil - Sticks",
    "startTime": 1729989807,
    "startTimeReadable": "Sun, 27 Oct 2024 00:43:27 GMT",
    "duration": 309
  },
  {
    "title": "7038634357 - Sink",
    "startTime": 1729990116,
    "startTimeReadable": "Sun, 27 Oct 2024 00:48:36 GMT",
    "duration": 231
  },
  {
    "title": "Asan Tone - Each Pool A Lifetime",
    "startTime": 1729990347,
    "startTimeReadable": "Sun, 27 Oct 2024 00:52:27 GMT",
    "duration": 30
  },
  {
    "title": "Vanessa Amara - Untitled Two",
    "startTime": 1729990377,
    "startTimeReadable": "Sun, 27 Oct 2024 00:52:57 GMT",
    "duration": 134
  },
  {
    "title": "DJ Metatron - If Only My Love Could Set U Free",
    "startTime": 1729990511,
    "startTimeReadable": "Sun, 27 Oct 2024 00:55:11 GMT",
    "duration": 406
  },
  {
    "title": "Scandinavian Star - Relic",
    "startTime": 1729990917,
    "startTimeReadable": "Sun, 27 Oct 2024 01:01:57 GMT",
    "duration": 104
  },
  {
    "title": "Emilia Haar - Yael",
    "startTime": 1729991021,
    "startTimeReadable": "Sun, 27 Oct 2024 01:03:41 GMT",
    "duration": 388
  },
  {
    "title": "ESP - LDM",
    "startTime": 1729991409,
    "startTimeReadable": "Sun, 27 Oct 2024 01:10:09 GMT",
    "duration": 145
  },
  {
    "title": "Oklou - oklou first tape - splash tape limited edition release - 01 face A ( best - nation - friendless )",
    "startTime": 1729991554,
    "startTimeReadable": "Sun, 27 Oct 2024 01:12:34 GMT",
    "duration": 365
  },
  {
    "title": "Dylan Henner - The Peach Tree Next Door Grew over Our Fence",
    "startTime": 1729991919,
    "startTimeReadable": "Sun, 27 Oct 2024 01:18:39 GMT",
    "duration": 339
  },
  {
    "title": "Christian Cosmos - _Immediately Sprang Up Because They Had No Depth Of Earth_",
    "startTime": 1729992258,
    "startTimeReadable": "Sun, 27 Oct 2024 01:24:18 GMT",
    "duration": 271
  },
  {
    "title": "Croatian Amor - Lovers In Flames",
    "startTime": 1729992529,
    "startTimeReadable": "Sun, 27 Oct 2024 01:28:49 GMT",
    "duration": 186
  },
  {
    "title": "Emilia Haar - Momiji",
    "startTime": 1729992715,
    "startTimeReadable": "Sun, 27 Oct 2024 01:31:55 GMT",
    "duration": 453
  },
  {
    "title": "Rikky Mandozza - Sunset in Stereo",
    "startTime": 1729993168,
    "startTimeReadable": "Sun, 27 Oct 2024 01:39:28 GMT",
    "duration": 453
  },
  {
    "title": "Croatian Amor - New Year",
    "startTime": 1729993621,
    "startTimeReadable": "Sun, 27 Oct 2024 01:47:01 GMT",
    "duration": 364
  },
  {
    "title": "piaconcept - Les Grues",
    "startTime": 1729993985,
    "startTimeReadable": "Sun, 27 Oct 2024 01:53:05 GMT",
    "duration": 323
  },
  {
    "title": "Medici Daughter, Raffy - Breeder",
    "startTime": 1729994308,
    "startTimeReadable": "Sun, 27 Oct 2024 01:58:28 GMT",
    "duration": 271
  },
  {
    "title": "Deapmash - Warfare",
    "startTime": 1729994579,
    "startTimeReadable": "Sun, 27 Oct 2024 02:02:59 GMT",
    "duration": 265
  },
  {
    "title": "Medici Daughter - Leash",
    "startTime": 1729994844,
    "startTimeReadable": "Sun, 27 Oct 2024 02:07:24 GMT",
    "duration": 127
  },
  {
    "title": "@-!3_&-7 9034-594 - Warter",
    "startTime": 1729994971,
    "startTimeReadable": "Sun, 27 Oct 2024 02:09:31 GMT",
    "duration": 276
  },
  {
    "title": "Croatian Amor - New Year",
    "startTime": 1729995247,
    "startTimeReadable": "Sun, 27 Oct 2024 02:14:07 GMT",
    "duration": 364
  },
  {
    "title": "NEXCYIA - Fade",
    "startTime": 1729995611,
    "startTimeReadable": "Sun, 27 Oct 2024 02:20:11 GMT",
    "duration": 355
  },
  {
    "title": "Maurice Schirm & Panksovic - Lack",
    "startTime": 1729995966,
    "startTimeReadable": "Sun, 27 Oct 2024 02:26:06 GMT",
    "duration": 221
  },
  {
    "title": "pal_unknown & Huong Federkeil - बलस्ट्रेड",
    "startTime": 1729996187,
    "startTimeReadable": "Sun, 27 Oct 2024 02:29:47 GMT",
    "duration": 305
  },
  {
    "title": "Medici Daughter - Leash",
    "startTime": 1729996492,
    "startTimeReadable": "Sun, 27 Oct 2024 02:34:52 GMT",
    "duration": 127
  },
  {
    "title": "@-!3_&-7 9034-594 - Warter",
    "startTime": 1729996619,
    "startTimeReadable": "Sun, 27 Oct 2024 02:36:59 GMT",
    "duration": 276
  },
  {
    "title": "piaconcept - Camouflage",
    "startTime": 1729996895,
    "startTimeReadable": "Sun, 27 Oct 2024 02:41:35 GMT",
    "duration": 314
  },
  {
    "title": "ESP - Voices",
    "startTime": 1729997209,
    "startTimeReadable": "Sun, 27 Oct 2024 02:46:49 GMT",
    "duration": 170
  },
  {
    "title": "Oklou - oklou first tape - splash tape limited edition release - 01 face A ( best - nation - friendless )",
    "startTime": 1729997379,
    "startTimeReadable": "Sun, 27 Oct 2024 02:49:39 GMT",
    "duration": 365
  },
  {
    "title": "Forest Casual - Crockerne Pill",
    "startTime": 1729997744,
    "startTimeReadable": "Sun, 27 Oct 2024 02:55:44 GMT",
    "duration": 273
  },
  {
    "title": "Vanessa Amara - Untitled Two",
    "startTime": 1729998017,
    "startTimeReadable": "Sun, 27 Oct 2024 03:00:17 GMT",
    "duration": 134
  },
  {
    "title": "Asan Tone - II",
    "startTime": 1729998151,
    "startTimeReadable": "Sun, 27 Oct 2024 03:02:31 GMT",
    "duration": 193
  },
  {
    "title": "GRAIL - Fierce Little Creatures",
    "startTime": 1729998344,
    "startTimeReadable": "Sun, 27 Oct 2024 03:05:44 GMT",
    "duration": 465
  },
  {
    "title": "Medici Daughter - Insolid",
    "startTime": 1729998809,
    "startTimeReadable": "Sun, 27 Oct 2024 03:13:29 GMT",
    "duration": 146
  },
  {
    "title": "Deapmash - Warfare",
    "startTime": 1729998955,
    "startTimeReadable": "Sun, 27 Oct 2024 03:15:55 GMT",
    "duration": 265
  },
  {
    "title": "pal_unknown & Huong Federkeil - बलस्ट्रेड",
    "startTime": 1729999220,
    "startTimeReadable": "Sun, 27 Oct 2024 03:20:20 GMT",
    "duration": 305
  },
  {
    "title": "Christian Cosmos - _Immediately Sprang Up Because They Had No Depth Of Earth_",
    "startTime": 1729999525,
    "startTimeReadable": "Sun, 27 Oct 2024 03:25:25 GMT",
    "duration": 271
  },
  {
    "title": "Daisuke Tanabe - Aftercloud",
    "startTime": 1729999796,
    "startTimeReadable": "Sun, 27 Oct 2024 03:29:56 GMT",
    "duration": 279
  },
  {
    "title": "Danity Kane - Ride For You (7038634357 remix)",
    "startTime": 1730000075,
    "startTimeReadable": "Sun, 27 Oct 2024 03:34:35 GMT",
    "duration": 231
  },
  {
    "title": "Maurice Schirm - ReworkCM (Half Time)",
    "startTime": 1730000306,
    "startTimeReadable": "Sun, 27 Oct 2024 03:38:26 GMT",
    "duration": 258
  },
  {
    "title": "kelman duran - FOREVA",
    "startTime": 1730000564,
    "startTimeReadable": "Sun, 27 Oct 2024 03:42:44 GMT",
    "duration": 332
  },
  {
    "title": "Croatian Amor - The World",
    "startTime": 1730000896,
    "startTimeReadable": "Sun, 27 Oct 2024 03:48:16 GMT",
    "duration": 183
  },
  {
    "title": "Danity Kane - Ride For You (7038634357 remix)",
    "startTime": 1730001079,
    "startTimeReadable": "Sun, 27 Oct 2024 03:51:19 GMT",
    "duration": 231
  },
  {
    "title": "Daisuke Tanabe - vintage 2008",
    "startTime": 1730001310,
    "startTimeReadable": "Sun, 27 Oct 2024 03:55:10 GMT",
    "duration": 358
  },
  {
    "title": "Orchid - Heavenly Memory",
    "startTime": 1730001668,
    "startTimeReadable": "Sun, 27 Oct 2024 04:01:08 GMT",
    "duration": 202
  },
  {
    "title": "WFST - Central Transfer Point",
    "startTime": 1730001870,
    "startTimeReadable": "Sun, 27 Oct 2024 04:04:30 GMT",
    "duration": 326
  },
  {
    "title": "Kidkanevil, Daisuke Tanabe - Sine Flowers",
    "startTime": 1730002196,
    "startTimeReadable": "Sun, 27 Oct 2024 04:09:56 GMT",
    "duration": 88
  },
  {
    "title": "ESP - Formation",
    "startTime": 1730002284,
    "startTimeReadable": "Sun, 27 Oct 2024 04:11:24 GMT",
    "duration": 149
  },
  {
    "title": "Scandinavian Star - Regal V",
    "startTime": 1730002433,
    "startTimeReadable": "Sun, 27 Oct 2024 04:13:53 GMT",
    "duration": 310
  },
  {
    "title": "Emilia Haar - Momiji",
    "startTime": 1730002743,
    "startTimeReadable": "Sun, 27 Oct 2024 04:19:03 GMT",
    "duration": 453
  },
  {
    "title": "piaconcept - Coaltar",
    "startTime": 1730003196,
    "startTimeReadable": "Sun, 27 Oct 2024 04:26:36 GMT",
    "duration": 335
  },
  {
    "title": "kelman duran - FOREVA",
    "startTime": 1730003531,
    "startTimeReadable": "Sun, 27 Oct 2024 04:32:11 GMT",
    "duration": 332
  },
  {
    "title": "Medici Daughter - Medici Chapel Nude",
    "startTime": 1730003863,
    "startTimeReadable": "Sun, 27 Oct 2024 04:37:43 GMT",
    "duration": 177
  },
  {
    "title": "Asan Tone - Perpetual Motion Via Jungle Transport",
    "startTime": 1730004040,
    "startTimeReadable": "Sun, 27 Oct 2024 04:40:40 GMT",
    "duration": 30
  },
  {
    "title": "DJ Metatron - If Only My Love Could Set U Free",
    "startTime": 1730004070,
    "startTimeReadable": "Sun, 27 Oct 2024 04:41:10 GMT",
    "duration": 406
  },
  {
    "title": "DJ Metatron - If Only My Love Could Set U Free",
    "startTime": 1730004476,
    "startTimeReadable": "Sun, 27 Oct 2024 04:47:56 GMT",
    "duration": 406
  },
  {
    "title": "aa3e4755i - c0012 becoming-anxious 175bpm",
    "startTime": 1730004882,
    "startTimeReadable": "Sun, 27 Oct 2024 04:54:42 GMT",
    "duration": 241
  },
  {
    "title": "NEXCYIA - motion man",
    "startTime": 1730005123,
    "startTimeReadable": "Sun, 27 Oct 2024 04:58:43 GMT",
    "duration": 324
  },
  {
    "title": "Alloy Sea, Mor Elian - We Will Never",
    "startTime": 1730005447,
    "startTimeReadable": "Sun, 27 Oct 2024 05:04:07 GMT",
    "duration": 177
  },
  {
    "title": "Hasfeldt - (I'm) Just Like The Others",
    "startTime": 1730005624,
    "startTimeReadable": "Sun, 27 Oct 2024 05:07:04 GMT",
    "duration": 185
  },
  {
    "title": "Shugo Noss - Highest In The Centrelink Line",
    "startTime": 1730005809,
    "startTimeReadable": "Sun, 27 Oct 2024 05:10:09 GMT",
    "duration": 366
  },
  {
    "title": "Danity Kane - Ride For You (7038634357 remix)",
    "startTime": 1730006175,
    "startTimeReadable": "Sun, 27 Oct 2024 05:16:15 GMT",
    "duration": 231
  },
  {
    "title": "Cyber Sonic - Machine Mystique",
    "startTime": 1730006406,
    "startTimeReadable": "Sun, 27 Oct 2024 05:20:06 GMT",
    "duration": 75
  },
  {
    "title": "Finn Klein - Östl. Zennwald",
    "startTime": 1730006481,
    "startTimeReadable": "Sun, 27 Oct 2024 05:21:21 GMT",
    "duration": 393
  },
  {
    "title": "Kidkanevil, Daisuke Tanabe - Harmonics, Pt. 2",
    "startTime": 1730006874,
    "startTimeReadable": "Sun, 27 Oct 2024 05:27:54 GMT",
    "duration": 217
  },
  {
    "title": "WFST - Central Transfer Point",
    "startTime": 1730007091,
    "startTimeReadable": "Sun, 27 Oct 2024 05:31:31 GMT",
    "duration": 326
  },
  {
    "title": "NEXCYIA - motion man",
    "startTime": 1730007417,
    "startTimeReadable": "Sun, 27 Oct 2024 05:36:57 GMT",
    "duration": 324
  },
  {
    "title": "Scandinavian Star - Regal V",
    "startTime": 1730007741,
    "startTimeReadable": "Sun, 27 Oct 2024 05:42:21 GMT",
    "duration": 310
  },
  {
    "title": "Christian Cosmos - _Immediately Sprang Up Because They Had No Depth Of Earth_",
    "startTime": 1730008051,
    "startTimeReadable": "Sun, 27 Oct 2024 05:47:31 GMT",
    "duration": 271
  },
  {
    "title": "GRAIL - Fierce Little Creatures",
    "startTime": 1730008322,
    "startTimeReadable": "Sun, 27 Oct 2024 05:52:02 GMT",
    "duration": 465
  },
  {
    "title": "Cyber Sonic - Datastream Dreams",
    "startTime": 1730008787,
    "startTimeReadable": "Sun, 27 Oct 2024 05:59:47 GMT",
    "duration": 64
  },
  {
    "title": "WFST - Cowboy",
    "startTime": 1730008851,
    "startTimeReadable": "Sun, 27 Oct 2024 06:00:51 GMT",
    "duration": 293
  },
  {
    "title": "Christian Cosmos - _Immediately Sprang Up Because They Had No Depth Of Earth_",
    "startTime": 1730009144,
    "startTimeReadable": "Sun, 27 Oct 2024 06:05:44 GMT",
    "duration": 271
  },
  {
    "title": "Scandinavian Star - Regal V",
    "startTime": 1730009415,
    "startTimeReadable": "Sun, 27 Oct 2024 06:10:15 GMT",
    "duration": 310
  },
  {
    "title": "Cyber Sonic - Machine Mystique",
    "startTime": 1730009725,
    "startTimeReadable": "Sun, 27 Oct 2024 06:15:25 GMT",
    "duration": 75
  },
  {
    "title": "Daisuke Tanabe - vintage 2008",
    "startTime": 1730009800,
    "startTimeReadable": "Sun, 27 Oct 2024 06:16:40 GMT",
    "duration": 358
  },
  {
    "title": "Asan Tone - Perpetual Motion Via Jungle Transport",
    "startTime": 1730010158,
    "startTimeReadable": "Sun, 27 Oct 2024 06:22:38 GMT",
    "duration": 30
  },
  {
    "title": "Kidkanevil, Daisuke Tanabe - MoOooOon",
    "startTime": 1730010188,
    "startTimeReadable": "Sun, 27 Oct 2024 06:23:08 GMT",
    "duration": 219
  },
  {
    "title": "Kidkanevil, Daisuke Tanabe - Ghostboy",
    "startTime": 1730010407,
    "startTimeReadable": "Sun, 27 Oct 2024 06:26:47 GMT",
    "duration": 203
  },
  {
    "title": "Hasfeldt - Let's Meet",
    "startTime": 1730010610,
    "startTimeReadable": "Sun, 27 Oct 2024 06:30:10 GMT",
    "duration": 260
  },
  {
    "title": "Medici Daughter - Leash",
    "startTime": 1730010870,
    "startTimeReadable": "Sun, 27 Oct 2024 06:34:30 GMT",
    "duration": 127
  },
  {
    "title": "Alloy Sea, Mor Elian - We Will Never",
    "startTime": 1730010997,
    "startTimeReadable": "Sun, 27 Oct 2024 06:36:37 GMT",
    "duration": 177
  },
  {
    "title": "aa3e4755i - c0002 expanding-into (177bpm)",
    "startTime": 1730011174,
    "startTimeReadable": "Sun, 27 Oct 2024 06:39:34 GMT",
    "duration": 161
  },
  {
    "title": "7038634357 - Sink",
    "startTime": 1730011335,
    "startTimeReadable": "Sun, 27 Oct 2024 06:42:15 GMT",
    "duration": 231
  },
  {
    "title": "aa3e4755i - c0012 becoming-anxious 175bpm",
    "startTime": 1730011566,
    "startTimeReadable": "Sun, 27 Oct 2024 06:46:06 GMT",
    "duration": 241
  },
  {
    "title": "Daisuke Tanabe - Fun Robbery",
    "startTime": 1730011807,
    "startTimeReadable": "Sun, 27 Oct 2024 06:50:07 GMT",
    "duration": 154
  },
  {
    "title": "piaconcept - Les Grues",
    "startTime": 1730011961,
    "startTimeReadable": "Sun, 27 Oct 2024 06:52:41 GMT",
    "duration": 323
  },
  {
    "title": "Deapmash - Warfare",
    "startTime": 1730012284,
    "startTimeReadable": "Sun, 27 Oct 2024 06:58:04 GMT",
    "duration": 265
  },
  {
    "title": "@-!3_&-7 9034-594 - Warter",
    "startTime": 1730012549,
    "startTimeReadable": "Sun, 27 Oct 2024 07:02:29 GMT",
    "duration": 276
  },
  {
    "title": "Maurice Schirm & Panksovic - Plethora",
    "startTime": 1730012825,
    "startTimeReadable": "Sun, 27 Oct 2024 07:07:05 GMT",
    "duration": 172
  },
  {
    "title": "Huong Federkeil - Sticks",
    "startTime": 1730012997,
    "startTimeReadable": "Sun, 27 Oct 2024 07:09:57 GMT",
    "duration": 309
  },
  {
    "title": "Cyber Sonic - Machine Mystique",
    "startTime": 1730013306,
    "startTimeReadable": "Sun, 27 Oct 2024 07:15:06 GMT",
    "duration": 75
  },
  {
    "title": "Kidkanevil, Daisuke Tanabe - Sine Flowers",
    "startTime": 1730013381,
    "startTimeReadable": "Sun, 27 Oct 2024 07:16:21 GMT",
    "duration": 88
  },
  {
    "title": "ESP - Vega",
    "startTime": 1730013469,
    "startTimeReadable": "Sun, 27 Oct 2024 07:17:49 GMT",
    "duration": 130
  },
  {
    "title": "Daisuke Tanabe - Gummed",
    "startTime": 1730013599,
    "startTimeReadable": "Sun, 27 Oct 2024 07:19:59 GMT",
    "duration": 242
  },
  {
    "title": "Asan Tone - Perpetual Motion Via Jungle Transport",
    "startTime": 1730013841,
    "startTimeReadable": "Sun, 27 Oct 2024 07:24:01 GMT",
    "duration": 30
  },
  {
    "title": "Finn Klein - Schmalholz",
    "startTime": 1730013871,
    "startTimeReadable": "Sun, 27 Oct 2024 07:24:31 GMT",
    "duration": 309
  },
  {
    "title": "piaconcept - Coaltar",
    "startTime": 1730014180,
    "startTimeReadable": "Sun, 27 Oct 2024 07:29:40 GMT",
    "duration": 335
  },
  {
    "title": "kelman duran - Plastika",
    "startTime": 1730014515,
    "startTimeReadable": "Sun, 27 Oct 2024 07:35:15 GMT",
    "duration": 187
  },
  {
    "title": "Scandinavian Star - Relic",
    "startTime": 1730014702,
    "startTimeReadable": "Sun, 27 Oct 2024 07:38:22 GMT",
    "duration": 104
  },
  {
    "title": "aa3e4755i - c0002 expanding-into (iarna 173bpm drone remix)",
    "startTime": 1730014806,
    "startTimeReadable": "Sun, 27 Oct 2024 07:40:06 GMT",
    "duration": 236
  },
  {
    "title": "Orchid - Heavenly Memory",
    "startTime": 1730015042,
    "startTimeReadable": "Sun, 27 Oct 2024 07:44:02 GMT",
    "duration": 202
  },
  {
    "title": "piaconcept - En bas de Tours",
    "startTime": 1730015244,
    "startTimeReadable": "Sun, 27 Oct 2024 07:47:24 GMT",
    "duration": 326
  },
  {
    "title": "Hasfeldt - Let's Meet",
    "startTime": 1730015570,
    "startTimeReadable": "Sun, 27 Oct 2024 07:52:50 GMT",
    "duration": 260
  },
  {
    "title": "Oklou - oklou first tape - splash tape limited edition release - 01 face A ( best - nation - friendless )",
    "startTime": 1730015830,
    "startTimeReadable": "Sun, 27 Oct 2024 07:57:10 GMT",
    "duration": 365
  },
  {
    "title": "Asan Tone - Visit from Tokay",
    "startTime": 1730016195,
    "startTimeReadable": "Sun, 27 Oct 2024 08:03:15 GMT",
    "duration": 30
  },
  {
    "title": "pal_unknown & Huong Federkeil - बलस्ट्रेड",
    "startTime": 1730016225,
    "startTimeReadable": "Sun, 27 Oct 2024 08:03:45 GMT",
    "duration": 305
  },
  {
    "title": "Croatian Amor - New Year",
    "startTime": 1730016530,
    "startTimeReadable": "Sun, 27 Oct 2024 08:08:50 GMT",
    "duration": 364
  },
  {
    "title": "Cyber Sonic - Techno Turbulence",
    "startTime": 1730016894,
    "startTimeReadable": "Sun, 27 Oct 2024 08:14:54 GMT",
    "duration": 73
  },
  {
    "title": "ESP - North",
    "startTime": 1730016967,
    "startTimeReadable": "Sun, 27 Oct 2024 08:16:07 GMT",
    "duration": 185
  },
  {
    "title": "Maurice Schirm & Panksovic - Plethora",
    "startTime": 1730017152,
    "startTimeReadable": "Sun, 27 Oct 2024 08:19:12 GMT",
    "duration": 172
  },
  {
    "title": "Alloy Sea, Mor Elian - We Will Never",
    "startTime": 1730017324,
    "startTimeReadable": "Sun, 27 Oct 2024 08:22:04 GMT",
    "duration": 177
  },
  {
    "title": "WFST - Kalt",
    "startTime": 1730017501,
    "startTimeReadable": "Sun, 27 Oct 2024 08:25:01 GMT",
    "duration": 304
  },
  {
    "title": "piaconcept - Camouflage",
    "startTime": 1730017805,
    "startTimeReadable": "Sun, 27 Oct 2024 08:30:05 GMT",
    "duration": 314
  },
  {
    "title": "NEXCYIA - Fade",
    "startTime": 1730018119,
    "startTimeReadable": "Sun, 27 Oct 2024 08:35:19 GMT",
    "duration": 355
  },
  {
    "title": "Kidkanevil, Daisuke Tanabe - MoOooOon",
    "startTime": 1730018474,
    "startTimeReadable": "Sun, 27 Oct 2024 08:41:14 GMT",
    "duration": 219
  },
  {
    "title": "WFST - Central Transfer Point",
    "startTime": 1730018693,
    "startTimeReadable": "Sun, 27 Oct 2024 08:44:53 GMT",
    "duration": 326
  },
  {
    "title": "Cyber Sonic - Techno Turbulence",
    "startTime": 1730019019,
    "startTimeReadable": "Sun, 27 Oct 2024 08:50:19 GMT",
    "duration": 73
  },
  {
    "title": "Croatian Amor - Transit",
    "startTime": 1730019092,
    "startTimeReadable": "Sun, 27 Oct 2024 08:51:32 GMT",
    "duration": 345
  },
  {
    "title": "Grand Inc - I Dont Live Here Anymore",
    "startTime": 1730019437,
    "startTimeReadable": "Sun, 27 Oct 2024 08:57:17 GMT",
    "duration": 283
  },
  {
    "title": "piaconcept - Coaltar",
    "startTime": 1730019720,
    "startTimeReadable": "Sun, 27 Oct 2024 09:02:00 GMT",
    "duration": 335
  },
  {
    "title": "ESP - North",
    "startTime": 1730020055,
    "startTimeReadable": "Sun, 27 Oct 2024 09:07:35 GMT",
    "duration": 185
  },
  {
    "title": "WFST - Kalt",
    "startTime": 1730020240,
    "startTimeReadable": "Sun, 27 Oct 2024 09:10:40 GMT",
    "duration": 304
  },
  {
    "title": "GRAIL - Day Two",
    "startTime": 1730020544,
    "startTimeReadable": "Sun, 27 Oct 2024 09:15:44 GMT",
    "duration": 349
  },
  {
    "title": "Weird Endgame - Cloaked Eating",
    "startTime": 1730020893,
    "startTimeReadable": "Sun, 27 Oct 2024 09:21:33 GMT",
    "duration": 249
  },
  {
    "title": "Asan Tone - II",
    "startTime": 1730021142,
    "startTimeReadable": "Sun, 27 Oct 2024 09:25:42 GMT",
    "duration": 193
  },
  {
    "title": "Maurice Schirm & Panksovic - Lack",
    "startTime": 1730021335,
    "startTimeReadable": "Sun, 27 Oct 2024 09:28:55 GMT",
    "duration": 221
  },
  {
    "title": "ESP - Formation",
    "startTime": 1730021556,
    "startTimeReadable": "Sun, 27 Oct 2024 09:32:36 GMT",
    "duration": 149
  },
  {
    "title": "Kidkanevil, Daisuke Tanabe - Sine Flowers",
    "startTime": 1730021705,
    "startTimeReadable": "Sun, 27 Oct 2024 09:35:05 GMT",
    "duration": 88
  },
  {
    "title": "Oklou - oklou first tape - splash tape limited edition release - 01 face A ( best - nation - friendless )",
    "startTime": 1730021793,
    "startTimeReadable": "Sun, 27 Oct 2024 09:36:33 GMT",
    "duration": 365
  },
  {
    "title": "Maurice Schirm - ReworkCM (Half Time)",
    "startTime": 1730022158,
    "startTimeReadable": "Sun, 27 Oct 2024 09:42:38 GMT",
    "duration": 258
  },
  {
    "title": "pal_unknown & Huong Federkeil - बलस्ट्रेड",
    "startTime": 1730022416,
    "startTimeReadable": "Sun, 27 Oct 2024 09:46:56 GMT",
    "duration": 305
  },
  {
    "title": "pal_unknown & Huong Federkeil - बलस्ट्रेड",
    "startTime": 1730022721,
    "startTimeReadable": "Sun, 27 Oct 2024 09:52:01 GMT",
    "duration": 305
  },
  {
    "title": "Croatian Amor - The World",
    "startTime": 1730023026,
    "startTimeReadable": "Sun, 27 Oct 2024 09:57:06 GMT",
    "duration": 183
  },
  {
    "title": "Medici Daughter - Leash",
    "startTime": 1730023209,
    "startTimeReadable": "Sun, 27 Oct 2024 10:00:09 GMT",
    "duration": 127
  },
  {
    "title": "Vanessa Amara - Untitled Three",
    "startTime": 1730023336,
    "startTimeReadable": "Sun, 27 Oct 2024 10:02:16 GMT",
    "duration": 101
  },
  {
    "title": "aa3e4755i - c0009 medium-convenience 164bpm",
    "startTime": 1730023437,
    "startTimeReadable": "Sun, 27 Oct 2024 10:03:57 GMT",
    "duration": 235
  },
  {
    "title": "piaconcept - Coaltar",
    "startTime": 1730023672,
    "startTimeReadable": "Sun, 27 Oct 2024 10:07:52 GMT",
    "duration": 335
  },
  {
    "title": "Medici Daughter - Snitch",
    "startTime": 1730024007,
    "startTimeReadable": "Sun, 27 Oct 2024 10:13:27 GMT",
    "duration": 118
  },
  {
    "title": "Kidkanevil, Daisuke Tanabe - Sine Flowers",
    "startTime": 1730024125,
    "startTimeReadable": "Sun, 27 Oct 2024 10:15:25 GMT",
    "duration": 88
  },
  {
    "title": "Vanessa Amara - Untitled Three",
    "startTime": 1730024213,
    "startTimeReadable": "Sun, 27 Oct 2024 10:16:53 GMT",
    "duration": 101
  },
  {
    "title": "Grand Inc - A Radiohead Sample",
    "startTime": 1730024314,
    "startTimeReadable": "Sun, 27 Oct 2024 10:18:34 GMT",
    "duration": 209
  },
  {
    "title": "Daisuke Tanabe - Ghost (2011)",
    "startTime": 1730024523,
    "startTimeReadable": "Sun, 27 Oct 2024 10:22:03 GMT",
    "duration": 173
  },
  {
    "title": "aa3e4755i - c0002 expanding-into (177bpm)",
    "startTime": 1730024696,
    "startTimeReadable": "Sun, 27 Oct 2024 10:24:56 GMT",
    "duration": 161
  },
  {
    "title": "Kidkanevil, Daisuke Tanabe - Ghostboy",
    "startTime": 1730024857,
    "startTimeReadable": "Sun, 27 Oct 2024 10:27:37 GMT",
    "duration": 203
  },
  {
    "title": "Vanity Productions - Shadows of Sleep",
    "startTime": 1730025060,
    "startTimeReadable": "Sun, 27 Oct 2024 10:31:00 GMT",
    "duration": 432
  },
  {
    "title": "ESP - Voices",
    "startTime": 1730025492,
    "startTimeReadable": "Sun, 27 Oct 2024 10:38:12 GMT",
    "duration": 170
  },
  {
    "title": "Kidkanevil, Daisuke Tanabe - Cherry Chimes",
    "startTime": 1730025662,
    "startTimeReadable": "Sun, 27 Oct 2024 10:41:02 GMT",
    "duration": 193
  },
  {
    "title": "Emilia Haar - Yael",
    "startTime": 1730025855,
    "startTimeReadable": "Sun, 27 Oct 2024 10:44:15 GMT",
    "duration": 388
  },
  {
    "title": "Medici Daughter - Snitch",
    "startTime": 1730026243,
    "startTimeReadable": "Sun, 27 Oct 2024 10:50:43 GMT",
    "duration": 118
  },
  {
    "title": "kelman duran - Rihanna X William Basinki II",
    "startTime": 1730026361,
    "startTimeReadable": "Sun, 27 Oct 2024 10:52:41 GMT",
    "duration": 250
  },
  {
    "title": "Grand Inc - A Radiohead Sample",
    "startTime": 1730026611,
    "startTimeReadable": "Sun, 27 Oct 2024 10:56:51 GMT",
    "duration": 209
  },
  {
    "title": "7038634357 - Sink",
    "startTime": 1730026820,
    "startTimeReadable": "Sun, 27 Oct 2024 11:00:20 GMT",
    "duration": 231
  },
  {
    "title": "Croatian Amor - New Year",
    "startTime": 1730027051,
    "startTimeReadable": "Sun, 27 Oct 2024 11:04:11 GMT",
    "duration": 364
  },
  {
    "title": "kelman duran - CIGS AND A VIEW",
    "startTime": 1730027415,
    "startTimeReadable": "Sun, 27 Oct 2024 11:10:15 GMT",
    "duration": 159
  },
  {
    "title": "pal_unknown & Huong Federkeil - बलस्ट्रेड",
    "startTime": 1730027574,
    "startTimeReadable": "Sun, 27 Oct 2024 11:12:54 GMT",
    "duration": 305
  },
  {
    "title": "Asan Tone - Perpetual Motion Via Jungle Transport",
    "startTime": 1730027879,
    "startTimeReadable": "Sun, 27 Oct 2024 11:17:59 GMT",
    "duration": 30
  },
  {
    "title": "Rikky Mandozza - Sunset in Stereo",
    "startTime": 1730027909,
    "startTimeReadable": "Sun, 27 Oct 2024 11:18:29 GMT",
    "duration": 453
  },
  {
    "title": "Oklou - oklou first tape - splash tape limited edition release - 01 face A ( best - nation - friendless )",
    "startTime": 1730028362,
    "startTimeReadable": "Sun, 27 Oct 2024 11:26:02 GMT",
    "duration": 365
  },
  {
    "title": "Asan Tone - Perpetual Motion Via Jungle Transport",
    "startTime": 1730028727,
    "startTimeReadable": "Sun, 27 Oct 2024 11:32:07 GMT",
    "duration": 30
  },
  {
    "title": "Emilia Haar - Yael",
    "startTime": 1730028757,
    "startTimeReadable": "Sun, 27 Oct 2024 11:32:37 GMT",
    "duration": 388
  },
  {
    "title": "Scandinavian Star - Regal V",
    "startTime": 1730029145,
    "startTimeReadable": "Sun, 27 Oct 2024 11:39:05 GMT",
    "duration": 310
  },
  {
    "title": "Maurice Schirm & Panksovic - Lack",
    "startTime": 1730029455,
    "startTimeReadable": "Sun, 27 Oct 2024 11:44:15 GMT",
    "duration": 221
  },
  {
    "title": "Oklou - oklou first tape - splash tape limited edition release - 02 face B ( Defeat )",
    "startTime": 1730029676,
    "startTimeReadable": "Sun, 27 Oct 2024 11:47:56 GMT",
    "duration": 361
  },
  {
    "title": "piaconcept - Coaltar",
    "startTime": 1730030037,
    "startTimeReadable": "Sun, 27 Oct 2024 11:53:57 GMT",
    "duration": 335
  },
  {
    "title": "Asan Tone - In Everyone Repeating",
    "startTime": 1730030372,
    "startTimeReadable": "Sun, 27 Oct 2024 11:59:32 GMT",
    "duration": 30
  },
  {
    "title": "Asan Tone - Visit from Tokay",
    "startTime": 1730030402,
    "startTimeReadable": "Sun, 27 Oct 2024 12:00:02 GMT",
    "duration": 30
  },
  {
    "title": "ESP - Formation",
    "startTime": 1730030432,
    "startTimeReadable": "Sun, 27 Oct 2024 12:00:32 GMT",
    "duration": 149
  },
  {
    "title": "ESP - Formation",
    "startTime": 1730030581,
    "startTimeReadable": "Sun, 27 Oct 2024 12:03:01 GMT",
    "duration": 149
  },
  {
    "title": "Kidkanevil, Daisuke Tanabe - Harmonics, Pt. 2",
    "startTime": 1730030730,
    "startTimeReadable": "Sun, 27 Oct 2024 12:05:30 GMT",
    "duration": 217
  },
  {
    "title": "Hasfeldt - (I'm) Just Like The Others",
    "startTime": 1730030947,
    "startTimeReadable": "Sun, 27 Oct 2024 12:09:07 GMT",
    "duration": 185
  },
  {
    "title": "Scandinavian Star - Alang",
    "startTime": 1730031132,
    "startTimeReadable": "Sun, 27 Oct 2024 12:12:12 GMT",
    "duration": 301
  },
  {
    "title": "Daisuke Tanabe - Gummed",
    "startTime": 1730031433,
    "startTimeReadable": "Sun, 27 Oct 2024 12:17:13 GMT",
    "duration": 242
  },
  {
    "title": "Finn Klein - Schmalholz",
    "startTime": 1730031675,
    "startTimeReadable": "Sun, 27 Oct 2024 12:21:15 GMT",
    "duration": 309
  },
  {
    "title": "Maurice Schirm - ReworkCM",
    "startTime": 1730031984,
    "startTimeReadable": "Sun, 27 Oct 2024 12:26:24 GMT",
    "duration": 251
  },
  {
    "title": "Orchid - Heavenly Memory",
    "startTime": 1730032235,
    "startTimeReadable": "Sun, 27 Oct 2024 12:30:35 GMT",
    "duration": 202
  },
  {
    "title": "Huong Federkeil - Sticks",
    "startTime": 1730032437,
    "startTimeReadable": "Sun, 27 Oct 2024 12:33:57 GMT",
    "duration": 309
  },
  {
    "title": "Kidkanevil, Daisuke Tanabe - Cherry Chimes",
    "startTime": 1730032746,
    "startTimeReadable": "Sun, 27 Oct 2024 12:39:06 GMT",
    "duration": 193
  },
  {
    "title": "Dylan Henner - The Peach Tree Next Door Grew over Our Fence",
    "startTime": 1730032939,
    "startTimeReadable": "Sun, 27 Oct 2024 12:42:19 GMT",
    "duration": 339
  },
  {
    "title": "Croatian Amor - New Year",
    "startTime": 1730033278,
    "startTimeReadable": "Sun, 27 Oct 2024 12:47:58 GMT",
    "duration": 364
  },
  {
    "title": "Hasfeldt - Let's Meet",
    "startTime": 1730033642,
    "startTimeReadable": "Sun, 27 Oct 2024 12:54:02 GMT",
    "duration": 260
  },
  {
    "title": "Medici Daughter - Gantz",
    "startTime": 1730033902,
    "startTimeReadable": "Sun, 27 Oct 2024 12:58:22 GMT",
    "duration": 174
  },
  {
    "title": "Weird Endgame - Cloaked Eating",
    "startTime": 1730034076,
    "startTimeReadable": "Sun, 27 Oct 2024 13:01:16 GMT",
    "duration": 249
  },
  {
    "title": "Oklou - oklou first tape - splash tape limited edition release - 01 face A ( best - nation - friendless )",
    "startTime": 1730034325,
    "startTimeReadable": "Sun, 27 Oct 2024 13:05:25 GMT",
    "duration": 365
  },
  {
    "title": "Cyber Sonic - Techno Turbulence",
    "startTime": 1730034690,
    "startTimeReadable": "Sun, 27 Oct 2024 13:11:30 GMT",
    "duration": 73
  },
  {
    "title": "Huong Federkeil - Sticks",
    "startTime": 1730034763,
    "startTimeReadable": "Sun, 27 Oct 2024 13:12:43 GMT",
    "duration": 309
  },
  {
    "title": "Maurice Schirm - ReworkCM (Half Time)",
    "startTime": 1730035072,
    "startTimeReadable": "Sun, 27 Oct 2024 13:17:52 GMT",
    "duration": 258
  },
  {
    "title": "Emilia Haar - Momiji",
    "startTime": 1730035330,
    "startTimeReadable": "Sun, 27 Oct 2024 13:22:10 GMT",
    "duration": 453
  },
  {
    "title": "Kidkanevil, Daisuke Tanabe - The Other Day We Thought of Our Friends",
    "startTime": 1730035783,
    "startTimeReadable": "Sun, 27 Oct 2024 13:29:43 GMT",
    "duration": 189
  },
  {
    "title": "Orchid - U Babe",
    "startTime": 1730035972,
    "startTimeReadable": "Sun, 27 Oct 2024 13:32:52 GMT",
    "duration": 178
  },
  {
    "title": "Orchid - U Babe",
    "startTime": 1730036150,
    "startTimeReadable": "Sun, 27 Oct 2024 13:35:50 GMT",
    "duration": 178
  },
  {
    "title": "kelman duran - CIGS AND A VIEW",
    "startTime": 1730036328,
    "startTimeReadable": "Sun, 27 Oct 2024 13:38:48 GMT",
    "duration": 159
  },
  {
    "title": "Cyber Sonic - Android Aura",
    "startTime": 1730036487,
    "startTimeReadable": "Sun, 27 Oct 2024 13:41:27 GMT",
    "duration": 79
  },
  {
    "title": "Asan Tone - In Everyone Repeating",
    "startTime": 1730036566,
    "startTimeReadable": "Sun, 27 Oct 2024 13:42:46 GMT",
    "duration": 30
  },
  {
    "title": "Dylan Henner - The Peach Tree Next Door Grew over Our Fence",
    "startTime": 1730036596,
    "startTimeReadable": "Sun, 27 Oct 2024 13:43:16 GMT",
    "duration": 339
  },
  {
    "title": "Danity Kane - Ride For You (7038634357 remix)",
    "startTime": 1730036935,
    "startTimeReadable": "Sun, 27 Oct 2024 13:48:55 GMT",
    "duration": 231
  },
  {
    "title": "Daisuke Tanabe - Hikemasen",
    "startTime": 1730037166,
    "startTimeReadable": "Sun, 27 Oct 2024 13:52:46 GMT",
    "duration": 407
  },
  {
    "title": "piaconcept - Coaltar",
    "startTime": 1730037573,
    "startTimeReadable": "Sun, 27 Oct 2024 13:59:33 GMT",
    "duration": 335
  },
  {
    "title": "Kidkanevil, Daisuke Tanabe - Super Deformed",
    "startTime": 1730037908,
    "startTimeReadable": "Sun, 27 Oct 2024 14:05:08 GMT",
    "duration": 239
  },
  {
    "title": "ESP - LDM",
    "startTime": 1730038147,
    "startTimeReadable": "Sun, 27 Oct 2024 14:09:07 GMT",
    "duration": 145
  },
  {
    "title": "Kidkanevil, Daisuke Tanabe - The Other Day We Thought of Our Friends",
    "startTime": 1730038292,
    "startTimeReadable": "Sun, 27 Oct 2024 14:11:32 GMT",
    "duration": 189
  },
  {
    "title": "Asan Tone - Perpetual Motion Via Jungle Transport",
    "startTime": 1730038481,
    "startTimeReadable": "Sun, 27 Oct 2024 14:14:41 GMT",
    "duration": 30
  },
  {
    "title": "ESP - North",
    "startTime": 1730038511,
    "startTimeReadable": "Sun, 27 Oct 2024 14:15:11 GMT",
    "duration": 185
  },
  {
    "title": "kelman duran - CIGS AND A VIEW",
    "startTime": 1730038696,
    "startTimeReadable": "Sun, 27 Oct 2024 14:18:16 GMT",
    "duration": 159
  },
  {
    "title": "Deapmash - Warfare",
    "startTime": 1730038855,
    "startTimeReadable": "Sun, 27 Oct 2024 14:20:55 GMT",
    "duration": 265
  },
  {
    "title": "Weird Endgame - Cloaked Eating",
    "startTime": 1730039120,
    "startTimeReadable": "Sun, 27 Oct 2024 14:25:20 GMT",
    "duration": 249
  },
  {
    "title": "GRAIL - Day Two",
    "startTime": 1730039369,
    "startTimeReadable": "Sun, 27 Oct 2024 14:29:29 GMT",
    "duration": 349
  },
  {
    "title": "Kidkanevil, Daisuke Tanabe - Super Deformed",
    "startTime": 1730039718,
    "startTimeReadable": "Sun, 27 Oct 2024 14:35:18 GMT",
    "duration": 239
  },
  {
    "title": "piaconcept - En bas de Tours",
    "startTime": 1730039957,
    "startTimeReadable": "Sun, 27 Oct 2024 14:39:17 GMT",
    "duration": 326
  },
  {
    "title": "kelman duran - Rihanna X William Basinki II",
    "startTime": 1730040283,
    "startTimeReadable": "Sun, 27 Oct 2024 14:44:43 GMT",
    "duration": 250
  },
  {
    "title": "NEXCYIA - hydro",
    "startTime": 1730040533,
    "startTimeReadable": "Sun, 27 Oct 2024 14:48:53 GMT",
    "duration": 283
  },
  {
    "title": "Daisuke Tanabe - Aftercloud",
    "startTime": 1730040816,
    "startTimeReadable": "Sun, 27 Oct 2024 14:53:36 GMT",
    "duration": 279
  },
  {
    "title": "Grand Inc - No Balance",
    "startTime": 1730041095,
    "startTimeReadable": "Sun, 27 Oct 2024 14:58:15 GMT",
    "duration": 289
  },
  {
    "title": "Finn Klein - Östl. Zennwald",
    "startTime": 1730041384,
    "startTimeReadable": "Sun, 27 Oct 2024 15:03:04 GMT",
    "duration": 393
  },
  {
    "title": "Kidkanevil, Daisuke Tanabe - The Other Day We Thought of Our Friends",
    "startTime": 1730041777,
    "startTimeReadable": "Sun, 27 Oct 2024 15:09:37 GMT",
    "duration": 189
  },
  {
    "title": "Oklou - oklou first tape - splash tape limited edition release - 02 face B ( Defeat )",
    "startTime": 1730041966,
    "startTimeReadable": "Sun, 27 Oct 2024 15:12:46 GMT",
    "duration": 361
  },
  {
    "title": "Medici Daughter - Leash",
    "startTime": 1730042327,
    "startTimeReadable": "Sun, 27 Oct 2024 15:18:47 GMT",
    "duration": 127
  },
  {
    "title": "Asan Tone - Perpetual Motion Via Jungle Transport",
    "startTime": 1730042454,
    "startTimeReadable": "Sun, 27 Oct 2024 15:20:54 GMT",
    "duration": 30
  },
  {
    "title": "Daisuke Tanabe - Fun Robbery",
    "startTime": 1730042484,
    "startTimeReadable": "Sun, 27 Oct 2024 15:21:24 GMT",
    "duration": 154
  },
  {
    "title": "Kidkanevil, Daisuke Tanabe - MoOooOon",
    "startTime": 1730042638,
    "startTimeReadable": "Sun, 27 Oct 2024 15:23:58 GMT",
    "duration": 219
  },
  {
    "title": "Shugo Noss - Highest In The Centrelink Line",
    "startTime": 1730042857,
    "startTimeReadable": "Sun, 27 Oct 2024 15:27:37 GMT",
    "duration": 366
  },
  {
    "title": "Orchid - Retrieval",
    "startTime": 1730043223,
    "startTimeReadable": "Sun, 27 Oct 2024 15:33:43 GMT",
    "duration": 275
  },
  {
    "title": "aa3e4755i - c0009 medium-convenience 164bpm",
    "startTime": 1730043498,
    "startTimeReadable": "Sun, 27 Oct 2024 15:38:18 GMT",
    "duration": 235
  },
  {
    "title": "aa3e4755i - c0012 becoming-anxious 175bpm",
    "startTime": 1730043733,
    "startTimeReadable": "Sun, 27 Oct 2024 15:42:13 GMT",
    "duration": 241
  },
  {
    "title": "Deapmash - Warfare",
    "startTime": 1730043974,
    "startTimeReadable": "Sun, 27 Oct 2024 15:46:14 GMT",
    "duration": 265
  },
  {
    "title": "Medici Daughter - Snitch",
    "startTime": 1730044239,
    "startTimeReadable": "Sun, 27 Oct 2024 15:50:39 GMT",
    "duration": 118
  },
  {
    "title": "NEXCYIA - Fade",
    "startTime": 1730044357,
    "startTimeReadable": "Sun, 27 Oct 2024 15:52:37 GMT",
    "duration": 355
  },
  {
    "title": "Kidkanevil, Daisuke Tanabe - MoOooOon",
    "startTime": 1730044712,
    "startTimeReadable": "Sun, 27 Oct 2024 15:58:32 GMT",
    "duration": 219
  },
  {
    "title": "kelman duran - CIGS AND A VIEW",
    "startTime": 1730044931,
    "startTimeReadable": "Sun, 27 Oct 2024 16:02:11 GMT",
    "duration": 159
  },
  {
    "title": "NEXCYIA - motion man",
    "startTime": 1730045090,
    "startTimeReadable": "Sun, 27 Oct 2024 16:04:50 GMT",
    "duration": 324
  },
  {
    "title": "piaconcept - Coaltar",
    "startTime": 1730045414,
    "startTimeReadable": "Sun, 27 Oct 2024 16:10:14 GMT",
    "duration": 335
  },
  {
    "title": "WFST - Central Transfer Point",
    "startTime": 1730045749,
    "startTimeReadable": "Sun, 27 Oct 2024 16:15:49 GMT",
    "duration": 326
  },
  {
    "title": "Orchid - Retrieval",
    "startTime": 1730046075,
    "startTimeReadable": "Sun, 27 Oct 2024 16:21:15 GMT",
    "duration": 275
  },
  {
    "title": "Danity Kane - Ride For You (7038634357 remix)",
    "startTime": 1730046350,
    "startTimeReadable": "Sun, 27 Oct 2024 16:25:50 GMT",
    "duration": 231
  },
  {
    "title": "Christian Cosmos - _Immediately Sprang Up Because They Had No Depth Of Earth_",
    "startTime": 1730046581,
    "startTimeReadable": "Sun, 27 Oct 2024 16:29:41 GMT",
    "duration": 271
  },
  {
    "title": "GRAIL - Day Two",
    "startTime": 1730046852,
    "startTimeReadable": "Sun, 27 Oct 2024 16:34:12 GMT",
    "duration": 349
  },
  {
    "title": "Asan Tone - To Tell A Picture",
    "startTime": 1730047201,
    "startTimeReadable": "Sun, 27 Oct 2024 16:40:01 GMT",
    "duration": 30
  },
  {
    "title": "Asan Tone - To Tell A Picture",
    "startTime": 1730047231,
    "startTimeReadable": "Sun, 27 Oct 2024 16:40:31 GMT",
    "duration": 30
  },
  {
    "title": "Croatian Amor - Transit",
    "startTime": 1730047261,
    "startTimeReadable": "Sun, 27 Oct 2024 16:41:01 GMT",
    "duration": 345
  },
  {
    "title": "Medici Daughter - Leash",
    "startTime": 1730047606,
    "startTimeReadable": "Sun, 27 Oct 2024 16:46:46 GMT",
    "duration": 127
  },
  {
    "title": "Deapmash - Warfare",
    "startTime": 1730047733,
    "startTimeReadable": "Sun, 27 Oct 2024 16:48:53 GMT",
    "duration": 265
  },
  {
    "title": "Medici Daughter - Insolid",
    "startTime": 1730047998,
    "startTimeReadable": "Sun, 27 Oct 2024 16:53:18 GMT",
    "duration": 146
  },
  {
    "title": "Oklou - oklou first tape - splash tape limited edition release - 01 face A ( best - nation - friendless )",
    "startTime": 1730048144,
    "startTimeReadable": "Sun, 27 Oct 2024 16:55:44 GMT",
    "duration": 365
  },
  {
    "title": "kelman duran - CIGS AND A VIEW",
    "startTime": 1730048509,
    "startTimeReadable": "Sun, 27 Oct 2024 17:01:49 GMT",
    "duration": 159
  },
  {
    "title": "Daisuke Tanabe - Fun Robbery",
    "startTime": 1730048668,
    "startTimeReadable": "Sun, 27 Oct 2024 17:04:28 GMT",
    "duration": 154
  },
  {
    "title": "Medici Daughter - Insolid",
    "startTime": 1730048822,
    "startTimeReadable": "Sun, 27 Oct 2024 17:07:02 GMT",
    "duration": 146
  },
  {
    "title": "Emilia Haar - Yael",
    "startTime": 1730048968,
    "startTimeReadable": "Sun, 27 Oct 2024 17:09:28 GMT",
    "duration": 388
  },
  {
    "title": "Scandinavian Star - Alang",
    "startTime": 1730049356,
    "startTimeReadable": "Sun, 27 Oct 2024 17:15:56 GMT",
    "duration": 301
  },
  {
    "title": "GRAIL - Fierce Little Creatures",
    "startTime": 1730049657,
    "startTimeReadable": "Sun, 27 Oct 2024 17:20:57 GMT",
    "duration": 465
  },
  {
    "title": "Daisuke Tanabe - Aftercloud",
    "startTime": 1730050122,
    "startTimeReadable": "Sun, 27 Oct 2024 17:28:42 GMT",
    "duration": 279
  },
  {
    "title": "aa3e4755i - c0002 expanding-into (177bpm)",
    "startTime": 1730050401,
    "startTimeReadable": "Sun, 27 Oct 2024 17:33:21 GMT",
    "duration": 161
  },
  {
    "title": "Maurice Schirm & Panksovic - Lack",
    "startTime": 1730050562,
    "startTimeReadable": "Sun, 27 Oct 2024 17:36:02 GMT",
    "duration": 221
  },
  {
    "title": "NEXCYIA - hydro",
    "startTime": 1730050783,
    "startTimeReadable": "Sun, 27 Oct 2024 17:39:43 GMT",
    "duration": 283
  },
  {
    "title": "Finn Klein - Schmalholz",
    "startTime": 1730051066,
    "startTimeReadable": "Sun, 27 Oct 2024 17:44:26 GMT",
    "duration": 309
  },
  {
    "title": "Cyber Sonic - Datastream Dreams",
    "startTime": 1730051375,
    "startTimeReadable": "Sun, 27 Oct 2024 17:49:35 GMT",
    "duration": 64
  },
  {
    "title": "Weird Endgame - Cloaked Eating",
    "startTime": 1730051439,
    "startTimeReadable": "Sun, 27 Oct 2024 17:50:39 GMT",
    "duration": 249
  },
  {
    "title": "Kidkanevil, Daisuke Tanabe - MoOooOon",
    "startTime": 1730051688,
    "startTimeReadable": "Sun, 27 Oct 2024 17:54:48 GMT",
    "duration": 219
  },
  {
    "title": "Cyber Sonic - Machine Mystique",
    "startTime": 1730051907,
    "startTimeReadable": "Sun, 27 Oct 2024 17:58:27 GMT",
    "duration": 75
  },
  {
    "title": "7038634357 - Square Heart",
    "startTime": 1730051982,
    "startTimeReadable": "Sun, 27 Oct 2024 17:59:42 GMT",
    "duration": 263
  },
  {
    "title": "Grand Inc - I Dont Live Here Anymore",
    "startTime": 1730052245,
    "startTimeReadable": "Sun, 27 Oct 2024 18:04:05 GMT",
    "duration": 283
  },
  {
    "title": "Scandinavian Star - Regal V",
    "startTime": 1730052528,
    "startTimeReadable": "Sun, 27 Oct 2024 18:08:48 GMT",
    "duration": 310
  },
  {
    "title": "NEXCYIA - motion man",
    "startTime": 1730052838,
    "startTimeReadable": "Sun, 27 Oct 2024 18:13:58 GMT",
    "duration": 324
  },
  {
    "title": "Kidkanevil, Daisuke Tanabe - Super Deformed",
    "startTime": 1730053162,
    "startTimeReadable": "Sun, 27 Oct 2024 18:19:22 GMT",
    "duration": 239
  },
  {
    "title": "Alloy Sea, Mor Elian - We Will Never",
    "startTime": 1730053401,
    "startTimeReadable": "Sun, 27 Oct 2024 18:23:21 GMT",
    "duration": 177
  },
  {
    "title": "DJ Metatron - If Only My Love Could Set U Free",
    "startTime": 1730053578,
    "startTimeReadable": "Sun, 27 Oct 2024 18:26:18 GMT",
    "duration": 406
  },
  {
    "title": "NEXCYIA - Fade",
    "startTime": 1730053984,
    "startTimeReadable": "Sun, 27 Oct 2024 18:33:04 GMT",
    "duration": 355
  },
  {
    "title": "Scandinavian Star - Relic",
    "startTime": 1730054339,
    "startTimeReadable": "Sun, 27 Oct 2024 18:38:59 GMT",
    "duration": 104
  },
  {
    "title": "7038634357 - Square Heart",
    "startTime": 1730054443,
    "startTimeReadable": "Sun, 27 Oct 2024 18:40:43 GMT",
    "duration": 263
  },
  {
    "title": "Orchid - U Babe",
    "startTime": 1730054706,
    "startTimeReadable": "Sun, 27 Oct 2024 18:45:06 GMT",
    "duration": 178
  },
  {
    "title": "Emilia Haar - Yael",
    "startTime": 1730054884,
    "startTimeReadable": "Sun, 27 Oct 2024 18:48:04 GMT",
    "duration": 388
  },
  {
    "title": "Cyber Sonic - Machine Mystique",
    "startTime": 1730055272,
    "startTimeReadable": "Sun, 27 Oct 2024 18:54:32 GMT",
    "duration": 75
  },
  {
    "title": "Kidkanevil, Daisuke Tanabe - Ghostboy",
    "startTime": 1730055347,
    "startTimeReadable": "Sun, 27 Oct 2024 18:55:47 GMT",
    "duration": 203
  },
  {
    "title": "GRAIL - Day Two",
    "startTime": 1730055550,
    "startTimeReadable": "Sun, 27 Oct 2024 18:59:10 GMT",
    "duration": 349
  },
  {
    "title": "aa3e4755i - c0002 expanding-into (177bpm)",
    "startTime": 1730055899,
    "startTimeReadable": "Sun, 27 Oct 2024 19:04:59 GMT",
    "duration": 161
  },
  {
    "title": "ESP - Vega",
    "startTime": 1730056060,
    "startTimeReadable": "Sun, 27 Oct 2024 19:07:40 GMT",
    "duration": 130
  },
  {
    "title": "Kidkanevil, Daisuke Tanabe - MoOooOon",
    "startTime": 1730056190,
    "startTimeReadable": "Sun, 27 Oct 2024 19:09:50 GMT",
    "duration": 219
  },
  {
    "title": "NEXCYIA - hydro",
    "startTime": 1730056409,
    "startTimeReadable": "Sun, 27 Oct 2024 19:13:29 GMT",
    "duration": 283
  },
  {
    "title": "piaconcept - En bas de Tours",
    "startTime": 1730056692,
    "startTimeReadable": "Sun, 27 Oct 2024 19:18:12 GMT",
    "duration": 326
  },
  {
    "title": "Croatian Amor - The World",
    "startTime": 1730057018,
    "startTimeReadable": "Sun, 27 Oct 2024 19:23:38 GMT",
    "duration": 183
  },
  {
    "title": "Vanessa Amara - Untitled Two",
    "startTime": 1730057201,
    "startTimeReadable": "Sun, 27 Oct 2024 19:26:41 GMT",
    "duration": 134
  },
  {
    "title": "Daisuke Tanabe - Ghost (2011)",
    "startTime": 1730057335,
    "startTimeReadable": "Sun, 27 Oct 2024 19:28:55 GMT",
    "duration": 173
  },
  {
    "title": "GRAIL - Fierce Little Creatures",
    "startTime": 1730057508,
    "startTimeReadable": "Sun, 27 Oct 2024 19:31:48 GMT",
    "duration": 465
  },
  {
    "title": "Croatian Amor - Transit",
    "startTime": 1730057973,
    "startTimeReadable": "Sun, 27 Oct 2024 19:39:33 GMT",
    "duration": 345
  },
  {
    "title": "WFST - Central Transfer Point",
    "startTime": 1730058318,
    "startTimeReadable": "Sun, 27 Oct 2024 19:45:18 GMT",
    "duration": 326
  },
  {
    "title": "Orchid - U Babe",
    "startTime": 1730058644,
    "startTimeReadable": "Sun, 27 Oct 2024 19:50:44 GMT",
    "duration": 178
  },
  {
    "title": "Maurice Schirm & Panksovic - Lack",
    "startTime": 1730058822,
    "startTimeReadable": "Sun, 27 Oct 2024 19:53:42 GMT",
    "duration": 221
  },
  {
    "title": "Scandinavian Star - Regal V",
    "startTime": 1730059043,
    "startTimeReadable": "Sun, 27 Oct 2024 19:57:23 GMT",
    "duration": 310
  },
  {
    "title": "Huong Federkeil - Sticks",
    "startTime": 1730059353,
    "startTimeReadable": "Sun, 27 Oct 2024 20:02:33 GMT",
    "duration": 309
  },
  {
    "title": "aa3e4755i - c0009 medium-convenience 164bpm",
    "startTime": 1730059662,
    "startTimeReadable": "Sun, 27 Oct 2024 20:07:42 GMT",
    "duration": 235
  },
  {
    "title": "Kidkanevil, Daisuke Tanabe - Sine Flowers",
    "startTime": 1730059897,
    "startTimeReadable": "Sun, 27 Oct 2024 20:11:37 GMT",
    "duration": 88
  },
  {
    "title": "Scandinavian Star - Alang",
    "startTime": 1730059985,
    "startTimeReadable": "Sun, 27 Oct 2024 20:13:05 GMT",
    "duration": 301
  },
  {
    "title": "Kidkanevil, Daisuke Tanabe - The Other Day We Thought of Our Friends",
    "startTime": 1730060286,
    "startTimeReadable": "Sun, 27 Oct 2024 20:18:06 GMT",
    "duration": 189
  },
  {
    "title": "Hasfeldt - (I'm) Just Like The Others",
    "startTime": 1730060475,
    "startTimeReadable": "Sun, 27 Oct 2024 20:21:15 GMT",
    "duration": 185
  },
  {
    "title": "Grand Inc - No Balance",
    "startTime": 1730060660,
    "startTimeReadable": "Sun, 27 Oct 2024 20:24:20 GMT",
    "duration": 289
  },
  {
    "title": "Cyber Sonic - Futuristic Frequencies",
    "startTime": 1730060949,
    "startTimeReadable": "Sun, 27 Oct 2024 20:29:09 GMT",
    "duration": 75
  },
  {
    "title": "Grand Inc - A Radiohead Sample",
    "startTime": 1730061024,
    "startTimeReadable": "Sun, 27 Oct 2024 20:30:24 GMT",
    "duration": 209
  },
  {
    "title": "Daisuke Tanabe - Fun Robbery",
    "startTime": 1730061233,
    "startTimeReadable": "Sun, 27 Oct 2024 20:33:53 GMT",
    "duration": 154
  },
  {
    "title": "Scandinavian Star - Regal V",
    "startTime": 1730061387,
    "startTimeReadable": "Sun, 27 Oct 2024 20:36:27 GMT",
    "duration": 310
  },
  {
    "title": "Scandinavian Star - Regal V",
    "startTime": 1730061697,
    "startTimeReadable": "Sun, 27 Oct 2024 20:41:37 GMT",
    "duration": 310
  },
  {
    "title": "Oklou - oklou first tape - splash tape limited edition release - 01 face A ( best - nation - friendless )",
    "startTime": 1730062007,
    "startTimeReadable": "Sun, 27 Oct 2024 20:46:47 GMT",
    "duration": 365
  },
  {
    "title": "piaconcept - En bas de Tours",
    "startTime": 1730062372,
    "startTimeReadable": "Sun, 27 Oct 2024 20:52:52 GMT",
    "duration": 326
  },
  {
    "title": "Daisuke Tanabe - Ghost (2011)",
    "startTime": 1730062698,
    "startTimeReadable": "Sun, 27 Oct 2024 20:58:18 GMT",
    "duration": 173
  },
  {
    "title": "aa3e4755i - c0002 expanding-into (177bpm)",
    "startTime": 1730062871,
    "startTimeReadable": "Sun, 27 Oct 2024 21:01:11 GMT",
    "duration": 161
  },
  {
    "title": "Daisuke Tanabe - vintage 2008",
    "startTime": 1730063032,
    "startTimeReadable": "Sun, 27 Oct 2024 21:03:52 GMT",
    "duration": 358
  },
  {
    "title": "Croatian Amor - New Year",
    "startTime": 1730063390,
    "startTimeReadable": "Sun, 27 Oct 2024 21:09:50 GMT",
    "duration": 364
  },
  {
    "title": "Cyber Sonic - Techno Turbulence",
    "startTime": 1730063754,
    "startTimeReadable": "Sun, 27 Oct 2024 21:15:54 GMT",
    "duration": 73
  },
  {
    "title": "piaconcept - En bas de Tours",
    "startTime": 1730063827,
    "startTimeReadable": "Sun, 27 Oct 2024 21:17:07 GMT",
    "duration": 326
  },
  {
    "title": "Cyber Sonic - Datastream Dreams",
    "startTime": 1730064153,
    "startTimeReadable": "Sun, 27 Oct 2024 21:22:33 GMT",
    "duration": 64
  },
  {
    "title": "Orchid - Retrieval",
    "startTime": 1730064217,
    "startTimeReadable": "Sun, 27 Oct 2024 21:23:37 GMT",
    "duration": 275
  },
  {
    "title": "Weird Endgame - Cloaked Eating",
    "startTime": 1730064492,
    "startTimeReadable": "Sun, 27 Oct 2024 21:28:12 GMT",
    "duration": 249
  },
  {
    "title": "Kidkanevil, Daisuke Tanabe - Harmonics, Pt. 2",
    "startTime": 1730064741,
    "startTimeReadable": "Sun, 27 Oct 2024 21:32:21 GMT",
    "duration": 217
  },
  {
    "title": "Maurice Schirm - ReworkCM",
    "startTime": 1730064958,
    "startTimeReadable": "Sun, 27 Oct 2024 21:35:58 GMT",
    "duration": 251
  },
  {
    "title": "pal_unknown & Huong Federkeil - बलस्ट्रेड",
    "startTime": 1730065209,
    "startTimeReadable": "Sun, 27 Oct 2024 21:40:09 GMT",
    "duration": 305
  },
  {
    "title": "kelman duran - Plastika",
    "startTime": 1730065514,
    "startTimeReadable": "Sun, 27 Oct 2024 21:45:14 GMT",
    "duration": 187
  },
  {
    "title": "Kidkanevil, Daisuke Tanabe - Harmonics, Pt. 1",
    "startTime": 1730065701,
    "startTimeReadable": "Sun, 27 Oct 2024 21:48:21 GMT",
    "duration": 147
  },
  {
    "title": "Danity Kane - Ride For You (7038634357 remix)",
    "startTime": 1730065848,
    "startTimeReadable": "Sun, 27 Oct 2024 21:50:48 GMT",
    "duration": 231
  },
  {
    "title": "WFST - Cowboy",
    "startTime": 1730066079,
    "startTimeReadable": "Sun, 27 Oct 2024 21:54:39 GMT",
    "duration": 293
  },
  {
    "title": "DJ Metatron - If Only My Love Could Set U Free",
    "startTime": 1730066372,
    "startTimeReadable": "Sun, 27 Oct 2024 21:59:32 GMT",
    "duration": 406
  },
  {
    "title": "Asan Tone - To Tell A Picture",
    "startTime": 1730066778,
    "startTimeReadable": "Sun, 27 Oct 2024 22:06:18 GMT",
    "duration": 30
  },
  {
    "title": "Daisuke Tanabe - Ghost (2011)",
    "startTime": 1730066808,
    "startTimeReadable": "Sun, 27 Oct 2024 22:06:48 GMT",
    "duration": 173
  },
  {
    "title": "GRAIL - Fierce Little Creatures",
    "startTime": 1730066981,
    "startTimeReadable": "Sun, 27 Oct 2024 22:09:41 GMT",
    "duration": 465
  },
  {
    "title": "Asan Tone - Each Pool A Lifetime",
    "startTime": 1730067446,
    "startTimeReadable": "Sun, 27 Oct 2024 22:17:26 GMT",
    "duration": 30
  },
  {
    "title": "Alloy Sea, Mor Elian - We Will Never",
    "startTime": 1730067476,
    "startTimeReadable": "Sun, 27 Oct 2024 22:17:56 GMT",
    "duration": 177
  },
  {
    "title": "Daisuke Tanabe - Aftercloud",
    "startTime": 1730067653,
    "startTimeReadable": "Sun, 27 Oct 2024 22:20:53 GMT",
    "duration": 279
  },
  {
    "title": "Sinemis - In the End",
    "startTime": 1730067932,
    "startTimeReadable": "Sun, 27 Oct 2024 22:25:32 GMT",
    "duration": 245
  },
  {
    "title": "Kidkanevil, Daisuke Tanabe - Sine Flowers",
    "startTime": 1730068177,
    "startTimeReadable": "Sun, 27 Oct 2024 22:29:37 GMT",
    "duration": 88
  },
  {
    "title": "Kidkanevil, Daisuke Tanabe - Cherry Chimes",
    "startTime": 1730068265,
    "startTimeReadable": "Sun, 27 Oct 2024 22:31:05 GMT",
    "duration": 193
  },
  {
    "title": "Croatian Amor - New Year",
    "startTime": 1730068458,
    "startTimeReadable": "Sun, 27 Oct 2024 22:34:18 GMT",
    "duration": 364
  },
  {
    "title": "Shugo Noss - Highest In The Centrelink Line",
    "startTime": 1730068822,
    "startTimeReadable": "Sun, 27 Oct 2024 22:40:22 GMT",
    "duration": 366
  },
  {
    "title": "Medici Daughter - Gantz",
    "startTime": 1730069188,
    "startTimeReadable": "Sun, 27 Oct 2024 22:46:28 GMT",
    "duration": 174
  },
  {
    "title": "Kidkanevil, Daisuke Tanabe - Sine Flowers",
    "startTime": 1730069362,
    "startTimeReadable": "Sun, 27 Oct 2024 22:49:22 GMT",
    "duration": 88
  },
  {
    "title": "Medici Daughter - Leash",
    "startTime": 1730069450,
    "startTimeReadable": "Sun, 27 Oct 2024 22:50:50 GMT",
    "duration": 127
  },
  {
    "title": "Cyber Sonic - Techno Turbulence",
    "startTime": 1730069577,
    "startTimeReadable": "Sun, 27 Oct 2024 22:52:57 GMT",
    "duration": 73
  },
  {
    "title": "GRAIL - Fierce Little Creatures",
    "startTime": 1730069650,
    "startTimeReadable": "Sun, 27 Oct 2024 22:54:10 GMT",
    "duration": 465
  },
  {
    "title": "Croatian Amor - New Year",
    "startTime": 1730070115,
    "startTimeReadable": "Sun, 27 Oct 2024 23:01:55 GMT",
    "duration": 364
  },
  {
    "title": "Huong Federkeil - Sticks",
    "startTime": 1730070479,
    "startTimeReadable": "Sun, 27 Oct 2024 23:07:59 GMT",
    "duration": 309
  },
  {
    "title": "Huong Federkeil - Sticks",
    "startTime": 1730070788,
    "startTimeReadable": "Sun, 27 Oct 2024 23:13:08 GMT",
    "duration": 309
  },
  {
    "title": "Hasfeldt - (I'm) Just Like The Others",
    "startTime": 1730071097,
    "startTimeReadable": "Sun, 27 Oct 2024 23:18:17 GMT",
    "duration": 185
  },
  {
    "title": "kelman duran - Plastika",
    "startTime": 1730071282,
    "startTimeReadable": "Sun, 27 Oct 2024 23:21:22 GMT",
    "duration": 187
  },
  {
    "title": "Hasfeldt - Let's Meet",
    "startTime": 1730071469,
    "startTimeReadable": "Sun, 27 Oct 2024 23:24:29 GMT",
    "duration": 260
  },
  {
    "title": "Medici Daughter - Leash",
    "startTime": 1730071729,
    "startTimeReadable": "Sun, 27 Oct 2024 23:28:49 GMT",
    "duration": 127
  },
  {
    "title": "Asan Tone - Each Pool A Lifetime",
    "startTime": 1730071856,
    "startTimeReadable": "Sun, 27 Oct 2024 23:30:56 GMT",
    "duration": 30
  },
  {
    "title": "Finn Klein - Östl. Zennwald",
    "startTime": 1730071886,
    "startTimeReadable": "Sun, 27 Oct 2024 23:31:26 GMT",
    "duration": 393
  },
  {
    "title": "Christian Cosmos - _Immediately Sprang Up Because They Had No Depth Of Earth_",
    "startTime": 1730072279,
    "startTimeReadable": "Sun, 27 Oct 2024 23:37:59 GMT",
    "duration": 271
  },
  {
    "title": "NEXCYIA - hydro",
    "startTime": 1730072550,
    "startTimeReadable": "Sun, 27 Oct 2024 23:42:30 GMT",
    "duration": 283
  },
  {
    "title": "Cyber Sonic - Machine Mystique",
    "startTime": 1730072833,
    "startTimeReadable": "Sun, 27 Oct 2024 23:47:13 GMT",
    "duration": 75
  },
  {
    "title": "Croatian Amor - Lovers In Flames",
    "startTime": 1730072908,
    "startTimeReadable": "Sun, 27 Oct 2024 23:48:28 GMT",
    "duration": 186
  },
  {
    "title": "Medici Daughter - Leash",
    "startTime": 1730073094,
    "startTimeReadable": "Sun, 27 Oct 2024 23:51:34 GMT",
    "duration": 127
  },
  {
    "title": "Daisuke Tanabe - vintage 2008",
    "startTime": 1730073221,
    "startTimeReadable": "Sun, 27 Oct 2024 23:53:41 GMT",
    "duration": 358
  }
]